[{"review_id": "7bb735d50c5eb453d1e6cc5ccf086915", "station_name": "IndianOil Petrol Pump (Dadar)", "station_address": "Hindu Colony, L N Road, near Ruia College, Dadar East, Mumbai, Maharashtra 400014", "station_rating": 4.0, "station_reviews": 696.0, "brand": "IndianOil", "category": "Petrol Pump", "zone": "Central Mumbai", "lat": 19.0227588, "lng": 72.848716, "author_name": "JAY SHAH", "rating": 5.0, "text": "Excellent service staff is very friendly and polite. Also the premises was kept clean.MAS has 4 products, MS, XP, HSD, XG and automotive oils.\n\nTyre shop, PUC.\n\nMechanical, car polish service.", "date_relative": "2 months ago", "date_iso": "2026-06-04T10:56:11.176005+00:00", "collected_at": "2026-06-04T10:56:11.176005+00:00", "source": "google_maps_scrape"}, {"review_id": "7bb735d50c5eb453d1e6cc5ccf086915", "station_name": "IndianOil Petrol Pump (Dadar)", "station_address": "Hindu Colony, L N Road, near Ruia College, Dadar East, Mumbai, Maharashtra 400014", "station_rating": 4.0, "station_reviews": 696.0, "brand": "IndianOil", "category": "Petrol Pump", "zone": "Central Mumbai", "lat": 19.0227588, "lng": 72.848716, "author_name": "JAY SHAH", "rating": 5.0, "text": "Excellent service staff is very friendly and polite. Also the premises was kept clean.MAS has 4 products, MS, XP, HSD, XG and automotive oils.\n\nTyre shop, PUC.\n\nMechanical, car polish service.", "date_relative": "2 months ago", "date_iso": "2026-06-04T10:56:11.176005+00:00", "collected_at": "2026-06-04T10:56:11.176005+00:00", "source": "google_maps_scrape"}, {"review_id": "94fd942af5950056561c7a521b3bc5c0", "station_name": "IndianOil Petrol Pump (Dadar)", "station_address": "Hindu Colony, L N Road, near Ruia College, Dadar East, Mumbai, Maharashtra 400014", "station_rating": 4.0, "station_reviews": 696.0, "brand": "IndianOil", "category": "Petrol Pump", "zone": "Central Mumbai", "lat": 19.0227588, "lng": 72.848716, "author_name": "Manoj Tiwari", "rating": 5.0, "text": "Excellent service! I'm happy with the work here\n\nservice is very quick and good. The staff is very helpful\n\nGreat experience! It saves time here 👍", "date_relative": "2 months ago", "date_iso": "2026-06-04T10:56:11.176005+00:00", "collected_at": "2026-06-04T10:56:11.176005+00:00", "source": "google_maps_scrape"}, {"review_id": "94fd942af5950056561c7a521b3bc5c0", "station_name": "IndianOil Petrol Pump (Dadar)", "station_address": "Hindu Colony, L N Road, near Ruia College, Dadar East, Mumbai, Maharashtra 400014", "station_rating": 4.0, "station_reviews": 696.0, "brand": "IndianOil", "category": "Petrol Pump", "zone": "Central Mumbai", "lat": 19.0227588, "lng": 72.848716, "author_name": "Manoj Tiwari", "rating": 5.0, "text": "Excellent service! I'm happy with the work here\n\nservice is very quick and good. The staff is very helpful\n\nGreat experience! It saves time here 👍", "date_relative": "2 months ago", "date_iso": "2026-06-04T10:56:11.176005+00:00", "collected_at": "2026-06-04T10:56:11.176005+00:00", "source": "google_maps_scrape"}, {"review_id": "71b50989e0d58d0a724c999906927e02", "station_name": "IndianOil Petrol Pump (Dadar)", "station_address": "Hindu Colony, L N Road, near Ruia College, Dadar East, Mumbai, Maharashtra 400014", "station_rating": 4.0, "station_reviews": 696.0, "brand": "IndianOil", "category": "Petrol Pump", "zone": "Central Mumbai", "lat": 19.0227588, "lng": 72.848716, "author_name": "Prathmesh Baikar", "rating": 5.0, "text": "I found this petrol pump neat, clean. Good house keeping. Nitrogen air facility, tyre shop, PUC. All in one.\n\nCourteous, well-mannered staff.", "date_relative": "2 months ago", "date_iso": "2026-06-04T10:56:11.176005+00:00", "collected_at": "2026-06-04T10:56:11.176005+00:00", "source": "google_maps_scrape"}, {"review_id": "71b50989e0d58d0a724c999906927e02", "station_name": "IndianOil Petrol Pump (Dadar)", "station_address": "Hindu Colony, L N Road, near Ruia College, Dadar East, Mumbai, Maharashtra 400014", "station_rating": 4.0, "station_reviews": 696.0, "brand": "IndianOil", "category": "Petrol Pump", "zone": "Central Mumbai", "lat": 19.0227588, "lng": 72.848716, "author_name": "Prathmesh Baikar", "rating": 5.0, "text": "I found this petrol pump neat, clean. Good house keeping. Nitrogen air facility, tyre shop, PUC. All in one.\n\nCourteous, well-mannered staff.", "date_relative": "2 months ago", "date_iso": "2026-06-04T10:56:11.176005+00:00", "collected_at": "2026-06-04T10:56:11.176005+00:00", "source": "google_maps_scrape"}, {"review_id": "d4f659a473be4f354ffc2d656e21dc17", "station_name": "IndianOil Petrol Pump (Dadar)", "station_address": "Hindu Colony, L N Road, near Ruia College, Dadar East, Mumbai, Maharashtra 400014", "station_rating": 4.0, "station_reviews": 696.0, "brand": "IndianOil", "category": "Petrol Pump", "zone": "Central Mumbai", "lat": 19.0227588, "lng": 72.848716, "author_name": "MILONI SHAH", "rating": 5.0, "text": "Excellent service very well managed n polite staff who sees to it the customer gets appropriate service", "date_relative": "2 months ago", "date_iso": "2026-06-04T10:56:11.176005+00:00", "collected_at": "2026-06-04T10:56:11.176005+00:00", "source": "google_maps_scrape"}, {"review_id": "d4f659a473be4f354ffc2d656e21dc17", "station_name": "IndianOil Petrol Pump (Dadar)", "station_address": "Hindu Colony, L N Road, near Ruia College, Dadar East, Mumbai, Maharashtra 400014", "station_rating": 4.0, "station_reviews": 696.0, "brand": "IndianOil", "category": "Petrol Pump", "zone": "Central Mumbai", "lat": 19.0227588, "lng": 72.848716, "author_name": "MILONI SHAH", "rating": 5.0, "text": "Excellent service very well managed n polite staff who sees to it the customer gets appropriate service", "date_relative": "2 months ago", "date_iso": "2026-06-04T10:56:11.176005+00:00", "collected_at": "2026-06-04T10:56:11.176005+00:00", "source": "google_maps_scrape"}, {"review_id": "e7f608f0495decb7f2d4de42d4eb0c4a", "station_name": "IndianOil Petrol Pump (Dadar)", "station_address": "Hindu Colony, L N Road, near Ruia College, Dadar East, Mumbai, Maharashtra 400014", "station_rating": 4.0, "station_reviews": 696.0, "brand": "IndianOil", "category": "Petrol Pump", "zone": "Central Mumbai", "lat": 19.0227588, "lng": 72.848716, "author_name": "Tanvi Minde", "rating": 1.0, "text": "Worst staff , rude ,arrogant even about their own mistake. No speaking manners, disrespectful, careless staff . Evening staff on date 10th January 2026 (6.30-7pm)", "date_relative": "4 months ago", "date_iso": "2026-06-04T10:56:11.176005+00:00", "collected_at": "2026-06-04T10:56:11.176005+00:00", "source": "google_maps_scrape"}, {"review_id": "e7f608f0495decb7f2d4de42d4eb0c4a", "station_name": "IndianOil Petrol Pump (Dadar)", "station_address": "Hindu Colony, L N Road, near Ruia College, Dadar East, Mumbai, Maharashtra 400014", "station_rating": 4.0, "station_reviews": 696.0, "brand": "IndianOil", "category": "Petrol Pump", "zone": "Central Mumbai", "lat": 19.0227588, "lng": 72.848716, "author_name": "Tanvi Minde", "rating": 1.0, "text": "Worst staff , rude ,arrogant even about their own mistake. No speaking manners, disrespectful, careless staff . Evening staff on date 10th January 2026 (6.30-7pm)", "date_relative": "4 months ago", "date_iso": "2026-06-04T10:56:11.176005+00:00", "collected_at": "2026-06-04T10:56:11.176005+00:00", "source": "google_maps_scrape"}, {"review_id": "b52b4563e284099734a2d814c6512d4f", "station_name": "IndianOil Petrol Pump (Dadar)", "station_address": "Hindu Colony, L N Road, near Ruia College, Dadar East, Mumbai, Maharashtra 400014", "station_rating": 4.0, "station_reviews": 696.0, "brand": "IndianOil", "category": "Petrol Pump", "zone": "Central Mumbai", "lat": 19.0227588, "lng": 72.848716, "author_name": "Yash singh", "rating": 5.0, "text": "Fast service\nPetrol diesel Quality best\nGood all staff\nGood Thailand", "date_relative": "2 months ago", "date_iso": "2026-06-04T10:56:11.176005+00:00", "collected_at": "2026-06-04T10:56:11.176005+00:00", "source": "google_maps_scrape"}, {"review_id": "b52b4563e284099734a2d814c6512d4f", "station_name": "IndianOil Petrol Pump (Dadar)", "station_address": "Hindu Colony, L N Road, near Ruia College, Dadar East, Mumbai, Maharashtra 400014", "station_rating": 4.0, "station_reviews": 696.0, "brand": "IndianOil", "category": "Petrol Pump", "zone": "Central Mumbai", "lat": 19.0227588, "lng": 72.848716, "author_name": "Yash singh", "rating": 5.0, "text": "Fast service\nPetrol diesel Quality best\nGood all staff\nGood Thailand", "date_relative": "2 months ago", "date_iso": "2026-06-04T10:56:11.176005+00:00", "collected_at": "2026-06-04T10:56:11.176005+00:00", "source": "google_maps_scrape"}, {"review_id": "1a96a7cac63bfb82cafc4098b70f169c", "station_name": "IndianOil Petrol Pump (Dadar)", "station_address": "Hindu Colony, L N Road, near Ruia College, Dadar East, Mumbai, Maharashtra 400014", "station_rating": 4.0, "station_reviews": 696.0, "brand": "IndianOil", "category": "Petrol Pump", "zone": "Central Mumbai", "lat": 19.0227588, "lng": 72.848716, "author_name": "Nirnay Kolabkar", "rating": 5.0, "text": "Best in class mostly trusted 95 fuel explained by dispensing person my car mileage has increased compared to normal fuel . Ask for x95 fuel", "date_relative": "7 months ago", "date_iso": "2026-06-04T10:56:11.176005+00:00", "collected_at": "2026-06-04T10:56:11.176005+00:00", "source": "google_maps_scrape"}, {"review_id": "1a96a7cac63bfb82cafc4098b70f169c", "station_name": "IndianOil Petrol Pump (Dadar)", "station_address": "Hindu Colony, L N Road, near Ruia College, Dadar East, Mumbai, Maharashtra 400014", "station_rating": 4.0, "station_reviews": 696.0, "brand": "IndianOil", "category": "Petrol Pump", "zone": "Central Mumbai", "lat": 19.0227588, "lng": 72.848716, "author_name": "Nirnay Kolabkar", "rating": 5.0, "text": "Best in class mostly trusted 95 fuel explained by dispensing person my car mileage has increased compared to normal fuel . Ask for x95 fuel", "date_relative": "7 months ago", "date_iso": "2026-06-04T10:56:11.176005+00:00", "collected_at": "2026-06-04T10:56:11.176005+00:00", "source": "google_maps_scrape"}, {"review_id": "dd4fb3f66fbcc2c51affd4dd95559e97", "station_name": "IndianOil Petrol Pump (Dadar)", "station_address": "Hindu Colony, L N Road, near Ruia College, Dadar East, Mumbai, Maharashtra 400014", "station_rating": 4.0, "station_reviews": 696.0, "brand": "IndianOil", "category": "Petrol Pump", "zone": "Central Mumbai", "lat": 19.0227588, "lng": 72.848716, "author_name": "Anurag", "rating": 5.0, "text": "Good Service and quality. Courteous staff.", "date_relative": "2 months ago", "date_iso": "2026-06-04T10:56:11.176005+00:00", "collected_at": "2026-06-04T10:56:11.176005+00:00", "source": "google_maps_scrape"}, {"review_id": "dd4fb3f66fbcc2c51affd4dd95559e97", "station_name": "IndianOil Petrol Pump (Dadar)", "station_address": "Hindu Colony, L N Road, near Ruia College, Dadar East, Mumbai, Maharashtra 400014", "station_rating": 4.0, "station_reviews": 696.0, "brand": "IndianOil", "category": "Petrol Pump", "zone": "Central Mumbai", "lat": 19.0227588, "lng": 72.848716, "author_name": "Anurag", "rating": 5.0, "text": "Good Service and quality. Courteous staff.", "date_relative": "2 months ago", "date_iso": "2026-06-04T10:56:11.176005+00:00", "collected_at": "2026-06-04T10:56:11.176005+00:00", "source": "google_maps_scrape"}, {"review_id": "9b0efb370add5710c496b497f86ca9f9", "station_name": "IndianOil Petrol Pump (Dadar)", "station_address": "Hindu Colony, L N Road, near Ruia College, Dadar East, Mumbai, Maharashtra 400014", "station_rating": 4.0, "station_reviews": 696.0, "brand": "IndianOil", "category": "Petrol Pump", "zone": "Central Mumbai", "lat": 19.0227588, "lng": 72.848716, "author_name": "Jairam Jaiswal", "rating": 5.0, "text": "Very nice service, very co opretive staff , nice and clran wash room", "date_relative": "2 months ago", "date_iso": "2026-06-04T10:56:11.176005+00:00", "collected_at": "2026-06-04T10:56:11.176005+00:00", "source": "google_maps_scrape"}, {"review_id": "9b0efb370add5710c496b497f86ca9f9", "station_name": "IndianOil Petrol Pump (Dadar)", "station_address": "Hindu Colony, L N Road, near Ruia College, Dadar East, Mumbai, Maharashtra 400014", "station_rating": 4.0, "station_reviews": 696.0, "brand": "IndianOil", "category": "Petrol Pump", "zone": "Central Mumbai", "lat": 19.0227588, "lng": 72.848716, "author_name": "Jairam Jaiswal", "rating": 5.0, "text": "Very nice service, very co opretive staff , nice and clran wash room", "date_relative": "2 months ago", "date_iso": "2026-06-04T10:56:11.176005+00:00", "collected_at": "2026-06-04T10:56:11.176005+00:00", "source": "google_maps_scrape"}, {"review_id": "d881e4091713f0eb0fdf702f23b8cb9b", "station_name": "IndianOil Petrol Pump (Dadar)", "station_address": "Hindu Colony, L N Road, near Ruia College, Dadar East, Mumbai, Maharashtra 400014", "station_rating": 4.0, "station_reviews": 696.0, "brand": "IndianOil", "category": "Petrol Pump", "zone": "Central Mumbai", "lat": 19.0227588, "lng": 72.848716, "author_name": "Rajagopal S.", "rating": 4.0, "text": "Good fuel quality ,free air pressure service. Car cleaning service is also available. Easy access and exit. No CNG. Tyre puncture service is also available. But most of the time only premium fuel is available and this causes inconvenience to normal fuel users.", "date_relative": "Edited 5 years ago", "date_iso": "2026-06-04T10:56:11.176005+00:00", "collected_at": "2026-06-04T10:56:11.176005+00:00", "source": "google_maps_scrape"}, {"review_id": "d881e4091713f0eb0fdf702f23b8cb9b", "station_name": "IndianOil Petrol Pump (Dadar)", "station_address": "Hindu Colony, L N Road, near Ruia College, Dadar East, Mumbai, Maharashtra 400014", "station_rating": 4.0, "station_reviews": 696.0, "brand": "IndianOil", "category": "Petrol Pump", "zone": "Central Mumbai", "lat": 19.0227588, "lng": 72.848716, "author_name": "Rajagopal S.", "rating": 4.0, "text": "Good fuel quality ,free air pressure service. Car cleaning service is also available. Easy access and exit. No CNG. Tyre puncture service is also available. But most of the time only premium fuel is available and this causes inconvenience to normal fuel users.", "date_relative": "Edited 5 years ago", "date_iso": "2026-06-04T10:56:11.176005+00:00", "collected_at": "2026-06-04T10:56:11.176005+00:00", "source": "google_maps_scrape"}]