[{"review_id": "fcbdbe9276a6e87cc29299574de1a089", "station_name": "Shell Petrol Pump", "station_address": "Tal - Kurla, Khairani Rd, Mumbai, Maharashtra 400072", "station_rating": 3.9, "station_reviews": 79.0, "brand": "Shell", "category": "Petrol Pump", "zone": "Eastern Suburbs", "lat": 19.106059, "lng": 72.888071, "author_name": "Gaurav Tripathi", "rating": 5.0, "text": "Staff and Services is good\n24 x 7 small shop as well inside petrol pump for water and snacks", "date_relative": "5 months ago", "date_iso": "2026-06-04T11:46:59.662198+00:00", "collected_at": "2026-06-04T11:46:59.662198+00:00", "source": "google_maps_scrape"}, {"review_id": "fcbdbe9276a6e87cc29299574de1a089", "station_name": "Shell Petrol Pump", "station_address": "Tal - Kurla, Khairani Rd, Mumbai, Maharashtra 400072", "station_rating": 3.9, "station_reviews": 79.0, "brand": "Shell", "category": "Petrol Pump", "zone": "Eastern Suburbs", "lat": 19.106059, "lng": 72.888071, "author_name": "Gaurav Tripathi", "rating": 5.0, "text": "Staff and Services is good\n24 x 7 small shop as well inside petrol pump for water and snacks", "date_relative": "5 months ago", "date_iso": "2026-06-04T11:46:59.662198+00:00", "collected_at": "2026-06-04T11:46:59.662198+00:00", "source": "google_maps_scrape"}, {"review_id": "1ce59c1a52df43219e3aa41075790509", "station_name": "Shell Petrol Pump", "station_address": "Tal - Kurla, Khairani Rd, Mumbai, Maharashtra 400072", "station_rating": 3.9, "station_reviews": 79.0, "brand": "Shell", "category": "Petrol Pump", "zone": "Eastern Suburbs", "lat": 19.106059, "lng": 72.888071, "author_name": "Chetan Jiandani", "rating": 5.0, "text": "Had a great experience was greeted with hello and was informed about difference of shell V power petrol and Normal shell petrol and advantages\nAlso was told about shell membership app\nSwapnil was a great guy good experience\n\nDid a Full Tank Of Shell VPower For My HONDA H’ness CB350\n\nKeep up the good work !", "date_relative": "3 years ago", "date_iso": "2026-06-04T11:46:59.662198+00:00", "collected_at": "2026-06-04T11:46:59.662198+00:00", "source": "google_maps_scrape"}, {"review_id": "1ce59c1a52df43219e3aa41075790509", "station_name": "Shell Petrol Pump", "station_address": "Tal - Kurla, Khairani Rd, Mumbai, Maharashtra 400072", "station_rating": 3.9, "station_reviews": 79.0, "brand": "Shell", "category": "Petrol Pump", "zone": "Eastern Suburbs", "lat": 19.106059, "lng": 72.888071, "author_name": "Chetan Jiandani", "rating": 5.0, "text": "Had a great experience was greeted with hello and was informed about difference of shell V power petrol and Normal shell petrol and advantages\nAlso was told about shell membership app\nSwapnil was a great guy good experience\n\nDid a Full Tank Of Shell VPower For My HONDA H’ness CB350\n\nKeep up the good work !", "date_relative": "3 years ago", "date_iso": "2026-06-04T11:46:59.662198+00:00", "collected_at": "2026-06-04T11:46:59.662198+00:00", "source": "google_maps_scrape"}, {"review_id": "7ce28b16fb449b3a3666872f9926b02c", "station_name": "Shell Petrol Pump", "station_address": "Tal - Kurla, Khairani Rd, Mumbai, Maharashtra 400072", "station_rating": 3.9, "station_reviews": 79.0, "brand": "Shell", "category": "Petrol Pump", "zone": "Eastern Suburbs", "lat": 19.106059, "lng": 72.888071, "author_name": "Jvc Coelho", "rating": 5.0, "text": "The employees, their greeting and the professional behaviour makes it very much lively. Of course the fuel is worth it.", "date_relative": "2 years ago", "date_iso": "2026-06-04T11:46:59.662198+00:00", "collected_at": "2026-06-04T11:46:59.662198+00:00", "source": "google_maps_scrape"}, {"review_id": "7ce28b16fb449b3a3666872f9926b02c", "station_name": "Shell Petrol Pump", "station_address": "Tal - Kurla, Khairani Rd, Mumbai, Maharashtra 400072", "station_rating": 3.9, "station_reviews": 79.0, "brand": "Shell", "category": "Petrol Pump", "zone": "Eastern Suburbs", "lat": 19.106059, "lng": 72.888071, "author_name": "Jvc Coelho", "rating": 5.0, "text": "The employees, their greeting and the professional behaviour makes it very much lively. Of course the fuel is worth it.", "date_relative": "2 years ago", "date_iso": "2026-06-04T11:46:59.662198+00:00", "collected_at": "2026-06-04T11:46:59.662198+00:00", "source": "google_maps_scrape"}, {"review_id": "ecd90cd460c6c3cbbb478e666deae4d7", "station_name": "Shell Petrol Pump", "station_address": "Tal - Kurla, Khairani Rd, Mumbai, Maharashtra 400072", "station_rating": 3.9, "station_reviews": 79.0, "brand": "Shell", "category": "Petrol Pump", "zone": "Eastern Suburbs", "lat": 19.106059, "lng": 72.888071, "author_name": "Abdulkarim Memon", "rating": 3.0, "text": "Please be advised that the price of fuel (petrol) is 12 rs costlier compared to other petrol pumps. It was 3 am, hence no option left other than to refuel it. The service is satisfactory and the staff are very courteous", "date_relative": "a year ago", "date_iso": "2026-06-04T11:46:59.662198+00:00", "collected_at": "2026-06-04T11:46:59.662198+00:00", "source": "google_maps_scrape"}, {"review_id": "ecd90cd460c6c3cbbb478e666deae4d7", "station_name": "Shell Petrol Pump", "station_address": "Tal - Kurla, Khairani Rd, Mumbai, Maharashtra 400072", "station_rating": 3.9, "station_reviews": 79.0, "brand": "Shell", "category": "Petrol Pump", "zone": "Eastern Suburbs", "lat": 19.106059, "lng": 72.888071, "author_name": "Abdulkarim Memon", "rating": 3.0, "text": "Please be advised that the price of fuel (petrol) is 12 rs costlier compared to other petrol pumps. It was 3 am, hence no option left other than to refuel it. The service is satisfactory and the staff are very courteous", "date_relative": "a year ago", "date_iso": "2026-06-04T11:46:59.662198+00:00", "collected_at": "2026-06-04T11:46:59.662198+00:00", "source": "google_maps_scrape"}, {"review_id": "0c9c0aa9207d90e2fbcb022bad761983", "station_name": "Shell Petrol Pump", "station_address": "Tal - Kurla, Khairani Rd, Mumbai, Maharashtra 400072", "station_rating": 3.9, "station_reviews": 79.0, "brand": "Shell", "category": "Petrol Pump", "zone": "Eastern Suburbs", "lat": 19.106059, "lng": 72.888071, "author_name": "Prayas Bhonde", "rating": 1.0, "text": "Very bad experience for all those services\nThere staff denied for washroom use", "date_relative": "a year ago", "date_iso": "2026-06-04T11:46:59.662198+00:00", "collected_at": "2026-06-04T11:46:59.662198+00:00", "source": "google_maps_scrape"}, {"review_id": "0c9c0aa9207d90e2fbcb022bad761983", "station_name": "Shell Petrol Pump", "station_address": "Tal - Kurla, Khairani Rd, Mumbai, Maharashtra 400072", "station_rating": 3.9, "station_reviews": 79.0, "brand": "Shell", "category": "Petrol Pump", "zone": "Eastern Suburbs", "lat": 19.106059, "lng": 72.888071, "author_name": "Prayas Bhonde", "rating": 1.0, "text": "Very bad experience for all those services\nThere staff denied for washroom use", "date_relative": "a year ago", "date_iso": "2026-06-04T11:46:59.662198+00:00", "collected_at": "2026-06-04T11:46:59.662198+00:00", "source": "google_maps_scrape"}, {"review_id": "12314fc83f78079cc297f9ffe34e6fc6", "station_name": "Shell Petrol Pump", "station_address": "Tal - Kurla, Khairani Rd, Mumbai, Maharashtra 400072", "station_rating": 3.9, "station_reviews": 79.0, "brand": "Shell", "category": "Petrol Pump", "zone": "Eastern Suburbs", "lat": 19.106059, "lng": 72.888071, "author_name": "Shreyas Sawant", "rating": 1.0, "text": "No difference of density in normal and v-power", "date_relative": "3 months ago", "date_iso": "2026-06-04T11:46:59.662198+00:00", "collected_at": "2026-06-04T11:46:59.662198+00:00", "source": "google_maps_scrape"}, {"review_id": "12314fc83f78079cc297f9ffe34e6fc6", "station_name": "Shell Petrol Pump", "station_address": "Tal - Kurla, Khairani Rd, Mumbai, Maharashtra 400072", "station_rating": 3.9, "station_reviews": 79.0, "brand": "Shell", "category": "Petrol Pump", "zone": "Eastern Suburbs", "lat": 19.106059, "lng": 72.888071, "author_name": "Shreyas Sawant", "rating": 1.0, "text": "No difference of density in normal and v-power", "date_relative": "3 months ago", "date_iso": "2026-06-04T11:46:59.662198+00:00", "collected_at": "2026-06-04T11:46:59.662198+00:00", "source": "google_maps_scrape"}, {"review_id": "3b4120e9ba34e96cab8c41faded827e1", "station_name": "Shell Petrol Pump", "station_address": "Tal - Kurla, Khairani Rd, Mumbai, Maharashtra 400072", "station_rating": 3.9, "station_reviews": 79.0, "brand": "Shell", "category": "Petrol Pump", "zone": "Eastern Suburbs", "lat": 19.106059, "lng": 72.888071, "author_name": "Gaurav Puria", "rating": 1.0, "text": "Petrol here is highly priced. No better quality or mileage", "date_relative": "8 months ago", "date_iso": "2026-06-04T11:46:59.662198+00:00", "collected_at": "2026-06-04T11:46:59.662198+00:00", "source": "google_maps_scrape"}, {"review_id": "3b4120e9ba34e96cab8c41faded827e1", "station_name": "Shell Petrol Pump", "station_address": "Tal - Kurla, Khairani Rd, Mumbai, Maharashtra 400072", "station_rating": 3.9, "station_reviews": 79.0, "brand": "Shell", "category": "Petrol Pump", "zone": "Eastern Suburbs", "lat": 19.106059, "lng": 72.888071, "author_name": "Gaurav Puria", "rating": 1.0, "text": "Petrol here is highly priced. No better quality or mileage", "date_relative": "8 months ago", "date_iso": "2026-06-04T11:46:59.662198+00:00", "collected_at": "2026-06-04T11:46:59.662198+00:00", "source": "google_maps_scrape"}, {"review_id": "2f4ccb1804be7a89e63aa7f6c874a5c9", "station_name": "Shell Petrol Pump", "station_address": "Tal - Kurla, Khairani Rd, Mumbai, Maharashtra 400072", "station_rating": 3.9, "station_reviews": 79.0, "brand": "Shell", "category": "Petrol Pump", "zone": "Eastern Suburbs", "lat": 19.106059, "lng": 72.888071, "author_name": "Mandar Nalawade", "rating": 5.0, "text": "I always love to fill my tank with Shell Fuels. Please increase your locations in Andheri East Mumbai. My car runs like sports car after using Shell Fuels. Simply superb quality of fuel worth filling tanks.", "date_relative": "a year ago", "date_iso": "2026-06-04T11:46:59.662198+00:00", "collected_at": "2026-06-04T11:46:59.662198+00:00", "source": "google_maps_scrape"}, {"review_id": "2f4ccb1804be7a89e63aa7f6c874a5c9", "station_name": "Shell Petrol Pump", "station_address": "Tal - Kurla, Khairani Rd, Mumbai, Maharashtra 400072", "station_rating": 3.9, "station_reviews": 79.0, "brand": "Shell", "category": "Petrol Pump", "zone": "Eastern Suburbs", "lat": 19.106059, "lng": 72.888071, "author_name": "Mandar Nalawade", "rating": 5.0, "text": "I always love to fill my tank with Shell Fuels. Please increase your locations in Andheri East Mumbai. My car runs like sports car after using Shell Fuels. Simply superb quality of fuel worth filling tanks.", "date_relative": "a year ago", "date_iso": "2026-06-04T11:46:59.662198+00:00", "collected_at": "2026-06-04T11:46:59.662198+00:00", "source": "google_maps_scrape"}, {"review_id": "21d5c900569bd0f4e543d76d0c8d7df5", "station_name": "Shell Petrol Pump", "station_address": "Tal - Kurla, Khairani Rd, Mumbai, Maharashtra 400072", "station_rating": 3.9, "station_reviews": 79.0, "brand": "Shell", "category": "Petrol Pump", "zone": "Eastern Suburbs", "lat": 19.106059, "lng": 72.888071, "author_name": "DANISH", "rating": 1.0, "text": "All staff present at place but still no one is ready to fill the fuel, saying it is company's rule we can not work for these 10 minutes. What is this rule for!!!\nNeither anywhere it is mentioned that petrol pump will be closed for that time!!! People in queue waiting for fuel from 10 minutes now extra 10 minutes for their bullish rule. Very disappointed!", "date_relative": "a year ago", "date_iso": "2026-06-04T11:46:59.662198+00:00", "collected_at": "2026-06-04T11:46:59.662198+00:00", "source": "google_maps_scrape"}, {"review_id": "21d5c900569bd0f4e543d76d0c8d7df5", "station_name": "Shell Petrol Pump", "station_address": "Tal - Kurla, Khairani Rd, Mumbai, Maharashtra 400072", "station_rating": 3.9, "station_reviews": 79.0, "brand": "Shell", "category": "Petrol Pump", "zone": "Eastern Suburbs", "lat": 19.106059, "lng": 72.888071, "author_name": "DANISH", "rating": 1.0, "text": "All staff present at place but still no one is ready to fill the fuel, saying it is company's rule we can not work for these 10 minutes. What is this rule for!!!\nNeither anywhere it is mentioned that petrol pump will be closed for that time!!! People in queue waiting for fuel from 10 minutes now extra 10 minutes for their bullish rule. Very disappointed!", "date_relative": "a year ago", "date_iso": "2026-06-04T11:46:59.662198+00:00", "collected_at": "2026-06-04T11:46:59.662198+00:00", "source": "google_maps_scrape"}, {"review_id": "58febc073f14a616193ae80167bc7178", "station_name": "Shell Petrol Pump", "station_address": "Tal - Kurla, Khairani Rd, Mumbai, Maharashtra 400072", "station_rating": 3.9, "station_reviews": 79.0, "brand": "Shell", "category": "Petrol Pump", "zone": "Eastern Suburbs", "lat": 19.106059, "lng": 72.888071, "author_name": "Sushant Sarphare", "rating": 1.0, "text": "Please make sure to gate the receipt of how much petrol your filling here because today (15 sept 2023) I am filling 750 rupees petrol after payment by card I was standing there for oil change the girl come to me and saying you are not paying the petrol money thank God the guy omkar who changing my oil saw the card in my hand he tell the girl please check your bag correctly after few minutes she get receipt in her bag only but it's very disappointment from shell petrol pump. I am living in Parel and  I come here only to fill out petrol but today's experience was not good.", "date_relative": "2 years ago", "date_iso": "2026-06-04T11:46:59.662198+00:00", "collected_at": "2026-06-04T11:46:59.662198+00:00", "source": "google_maps_scrape"}, {"review_id": "58febc073f14a616193ae80167bc7178", "station_name": "Shell Petrol Pump", "station_address": "Tal - Kurla, Khairani Rd, Mumbai, Maharashtra 400072", "station_rating": 3.9, "station_reviews": 79.0, "brand": "Shell", "category": "Petrol Pump", "zone": "Eastern Suburbs", "lat": 19.106059, "lng": 72.888071, "author_name": "Sushant Sarphare", "rating": 1.0, "text": "Please make sure to gate the receipt of how much petrol your filling here because today (15 sept 2023) I am filling 750 rupees petrol after payment by card I was standing there for oil change the girl come to me and saying you are not paying the petrol money thank God the guy omkar who changing my oil saw the card in my hand he tell the girl please check your bag correctly after few minutes she get receipt in her bag only but it's very disappointment from shell petrol pump. I am living in Parel and  I come here only to fill out petrol but today's experience was not good.", "date_relative": "2 years ago", "date_iso": "2026-06-04T11:46:59.662198+00:00", "collected_at": "2026-06-04T11:46:59.662198+00:00", "source": "google_maps_scrape"}]